exocounts/__init__.py
exocounts/convmag.py
exocounts/diflimit.py
exocounts/exocounts.py
exocounts/hz.py
exocounts/nstar.py
exocounts/planet.py
exocounts/readspec.py
exocounts/data/__init__.py
exocounts/data/mag.list
exocounts/old/__init__.py
exocounts/old/convmag.py
exocounts/old/ndark.py
exocounts/old/noisebudget.py
exocounts/old/nreadout.py
exocounts/old/nstar.py
exocounts/old/ntotal.py
exocounts/old/readspec.py
exocounts-0.1.0.dist-info/METADATA
exocounts-0.1.0.dist-info/WHEEL
exocounts-0.1.0.dist-info/top_level.txt
exocounts-0.1.0.dist-info/RECORD
