Metadata-Version: 2.1
Name: exocounts
Version: 0.1.0
Summary: UNKNOWN
Home-page: http://secondearths.sakura.ne.jp/exocounts/
Author: Hajime Kawahara and collaborators
Author-email: divrot@gmail.com
Maintainer: Hajime Kawahara and collaborators
Maintainer-email: divrot@gmail.com
License: MIT
Platform: UNKNOWN
Classifier: Programming Language :: Python
Requires-Dist: numpy
Requires-Dist: pandas
Requires-Dist: tqdm
Requires-Dist: scipy
Requires-Dist: astropy
Requires-Dist: gollum
